btwim/__init__.py
btwim/calinski_harabasz.py
btwim/utils.py
btwim-0.0.4.dist-info/LICENSE
btwim-0.0.4.dist-info/METADATA
btwim-0.0.4.dist-info/WHEEL
btwim-0.0.4.dist-info/top_level.txt
btwim-0.0.4.dist-info/RECORD
