Metadata-Version: 2.1
Name: btwim
Version: 0.0.4
Summary: Implementation of between dataset internal measures
Home-page: https://github.com/hj-n/btw-dataset-internal-measures
Author: Hyeon Jeon
Author-email: hj@hcil.snu.ac.kr
License: UNKNOWN
Platform: UNKNOWN
Classifier: Programming Language :: Python :: 3
Classifier: License :: OSI Approved :: MIT License
Classifier: Operating System :: OS Independent
Requires-Python: >=3.8
